{
    "kind": "한국스타벅스",
    "data": "20240226",
    "etag": "we82040320240226",
    "location": "세종특별자치시",
    "count": 14,
    "item": [
        {
            "name": "세종다정DT",
            "address": "세종특별자치시 다정북로 219 (다정동)"
        },
        {
            "name": "세종보람",
            "address": "세종특별자치시 한누리대로 2165 (보람동) A118,119,120,121,128,129,130,131"
        },
        {
            "name": "세종새롬",
            "address": "세종특별자치시  새롬중앙로 64 (새롬동)"
        },
        {
            "name": "세종어진R",
            "address": "세종특별자치시  한누리대로 499 (어진동)"
        },
        {
            "name": "세종종촌",
            "address": "세종특별자치시  도움3로 105-10 (종촌동) 성운프라자"
        },
        {
            "name": "세종첫마을",
            "address": "세종특별자치시  한누리대로 169 행복타워 1층"
        },
        {
            "name": "세종이마트",
            "address": "세종특별자치시 금송로 687(가람동 406) 이마트 세종점"
        },
        {
            "name": "세종청사",
            "address": "세종특별자치시  도움8로 81 (어진동)"
        },
        {
            "name": "세종아름",
            "address": "세종특별자치시 아름서1길 13-9 (아름동) 103,104,105,202,203호"
        },
        {
            "name": "세종반곡",
            "address": "세종특별자치시 한누리대로 1844 (반곡동)"
        },
        {
            "name": "세종한솔",
            "address": "세종특별자치시 노을3로 101 (한솔동)"
        },
        {
            "name": "세종소담",
            "address": "세종특별자치시 소담3로 8 (소담동) 1동  12호,13호,14호,15호,15a호,16호"
        },
        {
            "name": "세종금강DT",
            "address": "세종특별자치시 시청대로 45 (대평동)"
        },
        {
            "name": "세종충남대학교병원",
            "address": "세종특별자치시 보듬7로 20 (도담동) 헬스케어센터 1층"
        }
    ]
}